rktools/__init__.py
rktools/loggers.py
rktools/monitors.py
rktools/tests/__init__.py
rktools/tests/test_loggers.py
rktools/tests/test_monitors.py
rktools/tests/config/config.yaml
rktools/tests/config/empty.txt
rktools/tests/log/empty.txt
rktools-0.0.1.dist-info/LICENSE
rktools-0.0.1.dist-info/METADATA
rktools-0.0.1.dist-info/WHEEL
rktools-0.0.1.dist-info/top_level.txt
rktools-0.0.1.dist-info/RECORD
