Metadata-Version: 2.1
Name: rktools
Version: 0.0.1
Summary: The Régis Kla Python tools library
Home-page: https://github.com/rejux/rktools-lib
Author: Régis Kla
Author-email: klaregis@gmail.com
License: MIT
Platform: UNKNOWN
Classifier: License :: OSI Approved :: MIT License
Classifier: Programming Language :: Python :: 3
Classifier: Programming Language :: Python :: 3.7
Requires-Dist: tqdm
